setup.py
itzpip/__init__.py
itzpip/itz_time.py
itzpip.egg-info/PKG-INFO
itzpip.egg-info/SOURCES.txt
itzpip.egg-info/dependency_links.txt
itzpip.egg-info/top_level.txt
itzpip.egg-info/zip-safe