Metadata-Version: 1.1
Name: itzpip
Version: 0.0.4
Summary: itz libs
Home-page: UNKNOWN
Author: XinLi
Author-email: lixin@itouzi.com
License: MIT
Keywords: itz
Platform: UNKNOWN
Classifier: License :: OSI Approved :: MIT License
Classifier: Programming Language :: Python
Classifier: Intended Audience :: Developers
Classifier: Operating System :: OS Independent
